browser/__init__.py
browser/chrome.py
browser/firefox.py
browser/ie.py
qt4c/__init__.py
qt4c/accessible.py
qt4c/app.py
qt4c/control.py
qt4c/exceptions.py
qt4c/filedialog.py
qt4c/keyboard.py
qt4c/mouse.py
qt4c/qpath.py
qt4c/testcase.py
qt4c/uiacontrols.py
qt4c/util.py
qt4c/version.py
qt4c/webcontrols.py
qt4c/wincontrols.py
qt4c/wintypes.py
qt4c/webview/__init__.py
qt4c/webview/base.py
qt4c/webview/chromewebview/__init__.py
qt4c/webview/chromewebview/chromedriver.py
qt4c/webview/iewebview/__init__.py
qt4c/webview/iewebview/iedriver.py
qt4c-2.2.3.data/data/requirements.txt
qt4c-2.2.3.dist-info/LICENSE.TXT
qt4c-2.2.3.dist-info/METADATA
qt4c-2.2.3.dist-info/WHEEL
qt4c-2.2.3.dist-info/top_level.txt
qt4c-2.2.3.dist-info/RECORD
