Metadata-Version: 2.1
Name: qt4c
Version: 2.2.3
Summary: QTA test driver for Win32 application
Home-page: UNKNOWN
Author: Tencent
License: Copyright(c)2010-2018 Tencent All Rights Reserved. 
Platform: UNKNOWN
Classifier: Development Status :: 3 - Alpha
Classifier: Programming Language :: Python :: 2.7
Classifier: Operating System :: Microsoft :: Windows
License-File: LICENSE.TXT
Requires-Dist: qtaf (>=5.4.0)
Requires-Dist: Pillow
Requires-Dist: comtypes
Requires-Dist: websocket-client
Requires-Dist: pywin32 (<=224) ; sys_platform == "win32" and python_version <= "3.7"
Requires-Dist: pywin32 (==228) ; sys_platform == "win32" and python_version >= "3.8"
